Products.Sessions-6.0-py3.13-nspkg.pth
Products/Sessions/BrowserIdManager.py
Products/Sessions/SessionDataManager.py
Products/Sessions/SessionInterfaces.py
Products/Sessions/__init__.py
Products/Sessions/common.py
Products/Sessions/configure.zcml
Products/Sessions/interfaces.py
Products/Sessions/permissions.py
Products/Sessions/dtml/addDataManager.dtml
Products/Sessions/dtml/addIdManager.dtml
Products/Sessions/dtml/manageDataManager.dtml
Products/Sessions/dtml/manageIdManager.dtml
Products/Sessions/stresstests/stresstestMultiThread.py
Products/Sessions/tests/__init__.py
Products/Sessions/tests/testBrowserIdManager.py
Products/Sessions/tests/testInitialization.py
Products/Sessions/tests/testSessionDataManager.py
Products/Transience/Fake.py
Products/Transience/TransactionHelper.py
Products/Transience/Transience.py
Products/Transience/TransienceInterfaces.py
Products/Transience/TransientObject.py
Products/Transience/__init__.py
Products/Transience/interfaces.py
Products/Transience/permissions.py
Products/Transience/dtml/addTransientObjectContainer.dtml
Products/Transience/dtml/manageTransientObjectContainer.dtml
Products/Transience/tests/__init__.py
Products/Transience/tests/fauxtime.py
Products/Transience/tests/slowfauxtime.py
Products/Transience/tests/testTimeoutRelated.py
Products/Transience/tests/testTransactionHelper.py
Products/Transience/tests/testTransientObject.py
Products/Transience/tests/testTransientObjectContainer.py
products_sessions-6.0.dist-info/LICENSE.txt
products_sessions-6.0.dist-info/METADATA
products_sessions-6.0.dist-info/WHEEL
products_sessions-6.0.dist-info/entry_points.txt
products_sessions-6.0.dist-info/namespace_packages.txt
products_sessions-6.0.dist-info/top_level.txt
products_sessions-6.0.dist-info/RECORD
