Metadata-Version: 2.2
Name: Products.Sessions
Version: 6.0
Summary: Zope session management.
Home-page: https://github.com/zopefoundation/Products.Sessions/
Author: Zope Foundation and Contributors
Author-email: zope-dev@zope.dev
License: ZPL-2.1
Project-URL: Issue Tracker, https://github.com/zopefoundation/Products.Sessions/issues
Project-URL: Sources, https://github.com/zopefoundation/Products.Sessions
Keywords: Zope sessions management Transience product ZMI
Classifier: Development Status :: 6 - Mature
Classifier: Environment :: Web Environment
Classifier: Framework :: Zope
Classifier: Framework :: Zope :: 4
Classifier: Framework :: Zope :: 5
Classifier: License :: OSI Approved :: Zope Public License
Classifier: Operating System :: OS Independent
Classifier: Programming Language :: Python
Classifier: Programming Language :: Python :: 3
Classifier: Programming Language :: Python :: 3.9
Classifier: Programming Language :: Python :: 3.10
Classifier: Programming Language :: Python :: 3.11
Classifier: Programming Language :: Python :: 3.12
Classifier: Programming Language :: Python :: 3.13
Classifier: Programming Language :: Python :: Implementation :: CPython
Requires-Python: >=3.9
License-File: LICENSE.txt
Requires-Dist: setuptools
Requires-Dist: AccessControl
Requires-Dist: Acquisition
Requires-Dist: persistent
Requires-Dist: Persistence
Requires-Dist: transaction
Requires-Dist: ZODB
Requires-Dist: Zope>=4.0b5
Requires-Dist: zope.interface
Requires-Dist: zope.deferredimport
Provides-Extra: tests
Requires-Dist: Products.TemporaryFolder>=6.2; extra == "tests"
Dynamic: author
Dynamic: author-email
Dynamic: classifier
Dynamic: description
Dynamic: description-content-type
Dynamic: home-page
Dynamic: keywords
Dynamic: license
Dynamic: project-url
Dynamic: provides-extra
Dynamic: requires-dist
Dynamic: requires-python
Dynamic: summary
